{
  "hook_callpath": "new",
  "repository": {
    "name": "test3",
    "issue_comment_url": "https://api.github.com/repos/kbarber/test3/issues/comments/{number}",
    "git_tags_url": "https://api.github.com/repos/kbarber/test3/git/tags{/sha}",
    "open_issues_count": 1,
    "events_url": "https://api.github.com/repos/kbarber/test3/events",
    "assignees_url": "https://api.github.com/repos/kbarber/test3/assignees{/user}",
    "size": 108,
    "issues_url": "https://api.github.com/repos/kbarber/test3/issues{/number}",
    "has_wiki": true,
    "forks_count": 0,
    "created_at": "2013-01-26T12:04:02Z",
    "hooks_url": "https://api.github.com/repos/kbarber/test3/hooks",
    "git_commits_url": "https://api.github.com/repos/kbarber/test3/git/commits{/sha}",
    "subscription_url": "https://api.github.com/repos/kbarber/test3/subscription",
    "clone_url": "https://github.com/kbarber/test3.git",
    "tags_url": "https://api.github.com/repos/kbarber/test3/tags{/tag}",
    "branches_url": "https://api.github.com/repos/kbarber/test3/branches{/branch}",
    "merges_url": "https://api.github.com/repos/kbarber/test3/merges",
    "private": false,
    "contents_url": "https://api.github.com/repos/kbarber/test3/contents/{+path}",
    "watchers": 0,
    "forks_url": "https://api.github.com/repos/kbarber/test3/forks",
    "updated_at": "2013-01-27T14:54:09Z",
    "labels_url": "https://api.github.com/repos/kbarber/test3/labels{/name}",
    "issue_events_url": "https://api.github.com/repos/kbarber/test3/issues/events{/number}",
    "git_url": "git://github.com/kbarber/test3.git",
    "fork": false,
    "language": null,
    "notifications_url": "https://api.github.com/repos/kbarber/test3/notifications{?since,all,participating}",
    "languages_url": "https://api.github.com/repos/kbarber/test3/languages",
    "ssh_url": "git@github.com:kbarber/test3.git",
    "keys_url": "https://api.github.com/repos/kbarber/test3/keys{/key_id}",
    "url": "https://api.github.com/repos/kbarber/test3",
    "downloads_url": "https://api.github.com/repos/kbarber/test3/downloads",
    "id": 7837101,
    "svn_url": "https://github.com/kbarber/test3",
    "pushed_at": "2013-01-26T12:12:02Z",
    "commits_url": "https://api.github.com/repos/kbarber/test3/commits{/sha}",
    "mirror_url": null,
    "has_downloads": true,
    "comments_url": "https://api.github.com/repos/kbarber/test3/comments{/number}",
    "open_issues": 1,
    "trees_url": "https://api.github.com/repos/kbarber/test3/git/trees{/sha}",
    "full_name": "kbarber/test3",
    "git_refs_url": "https://api.github.com/repos/kbarber/test3/git/refs{/sha}",
    "has_issues": true,
    "archive_url": "https://api.github.com/repos/kbarber/test3/{archive_format}{/ref}",
    "collaborators_url": "https://api.github.com/repos/kbarber/test3/collaborators{/collaborator}",
    "homepage": null,
    "statuses_url": "https://api.github.com/repos/kbarber/test3/statuses/{sha}",
    "stargazers_url": "https://api.github.com/repos/kbarber/test3/stargazers",
    "forks": 0,
    "description": "",
    "teams_url": "https://api.github.com/repos/kbarber/test3/teams",
    "watchers_count": 0,
    "html_url": "https://github.com/kbarber/test3",
    "subscribers_url": "https://api.github.com/repos/kbarber/test3/subscribers",
    "contributors_url": "https://api.github.com/repos/kbarber/test3/contributors",
    "pulls_url": "https://api.github.com/repos/kbarber/test3/pulls{/number}",
    "milestones_url": "https://api.github.com/repos/kbarber/test3/milestones{/number}",
    "blobs_url": "https://api.github.com/repos/kbarber/test3/git/blobs{/sha}",
    "owner": {
      "avatar_url": "https://secure.gravatar.com/avatar/9accebe46504a4777d7b3c9707549dc6?d=https://a248.e.akamai.net/assets.github.com%2Fimages%2Fgravatars%2Fgravatar-user-420.png",
      "gists_url": "https://api.github.com/users/kbarber/gists{/gist_id}",
      "received_events_url": "https://api.github.com/users/kbarber/received_events",
      "gravatar_id": "9accebe46504a4777d7b3c9707549dc6",
      "events_url": "https://api.github.com/users/kbarber/events{/privacy}",
      "starred_url": "https://api.github.com/users/kbarber/starred{/owner}{/repo}",
      "url": "https://api.github.com/users/kbarber",
      "id": 80595,
      "following_url": "https://api.github.com/users/kbarber/following",
      "subscriptions_url": "https://api.github.com/users/kbarber/subscriptions",
      "type": "User",
      "organizations_url": "https://api.github.com/users/kbarber/orgs",
      "repos_url": "https://api.github.com/users/kbarber/repos",
      "followers_url": "https://api.github.com/users/kbarber/followers",
      "login": "kbarber"
    },
    "compare_url": "https://api.github.com/repos/kbarber/test3/compare/{base}...{head}"
  },
  "sender": {
    "avatar_url": "https://secure.gravatar.com/avatar/9accebe46504a4777d7b3c9707549dc6?d=https://a248.e.akamai.net/assets.github.com%2Fimages%2Fgravatars%2Fgravatar-user-420.png",
    "gists_url": "https://api.github.com/users/kbarber/gists{/gist_id}",
    "received_events_url": "https://api.github.com/users/kbarber/received_events",
    "gravatar_id": "9accebe46504a4777d7b3c9707549dc6",
    "events_url": "https://api.github.com/users/kbarber/events{/privacy}",
    "starred_url": "https://api.github.com/users/kbarber/starred{/owner}{/repo}",
    "url": "https://api.github.com/users/kbarber",
    "id": 80595,
    "following_url": "https://api.github.com/users/kbarber/following",
    "subscriptions_url": "https://api.github.com/users/kbarber/subscriptions",
    "type": "User",
    "organizations_url": "https://api.github.com/users/kbarber/orgs",
    "repos_url": "https://api.github.com/users/kbarber/repos",
    "followers_url": "https://api.github.com/users/kbarber/followers",
    "login": "kbarber"
  },
  "action": "reopened",
  "issue": {
    "events_url": "https://api.github.com/repos/kbarber/test3/issues/10/events",
    "number": 10,
    "pull_request": {
      "diff_url": null,
      "patch_url": null,
      "html_url": null
    },
    "created_at": "2013-01-27T14:54:44Z",
    "title": "test 1",
    "body": "",
    "comments": 2,
    "updated_at": "2013-01-27T14:55:48Z",
    "url": "https://api.github.com/repos/kbarber/test3/issues/10",
    "labels_url": "https://api.github.com/repos/kbarber/test3/issues/10/labels{/name}",
    "id": 10354565,
    "comments_url": "https://api.github.com/repos/kbarber/test3/issues/10/comments",
    "assignee": null,
    "milestone": null,
    "closed_at": null,
    "user": {
      "avatar_url": "https://secure.gravatar.com/avatar/9accebe46504a4777d7b3c9707549dc6?d=https://a248.e.akamai.net/assets.github.com%2Fimages%2Fgravatars%2Fgravatar-user-420.png",
      "gravatar_id": "9accebe46504a4777d7b3c9707549dc6",
      "gists_url": "https://api.github.com/users/kbarber/gists{/gist_id}",
      "received_events_url": "https://api.github.com/users/kbarber/received_events",
      "events_url": "https://api.github.com/users/kbarber/events{/privacy}",
      "url": "https://api.github.com/users/kbarber",
      "starred_url": "https://api.github.com/users/kbarber/starred{/owner}{/repo}",
      "id": 80595,
      "following_url": "https://api.github.com/users/kbarber/following",
      "type": "User",
      "subscriptions_url": "https://api.github.com/users/kbarber/subscriptions",
      "organizations_url": "https://api.github.com/users/kbarber/orgs",
      "repos_url": "https://api.github.com/users/kbarber/repos",
      "login": "kbarber",
      "followers_url": "https://api.github.com/users/kbarber/followers"
    },
    "html_url": "https://github.com/kbarber/test3/issues/10",
    "labels": [

    ],
    "state": "open"
  }
}
